{"translation":{"id":"ind_web","name":"World English Bible Terjemahan AI","shortName":"WEB-AI","englishName":"Indonesian AI Translated WEB","language":"ind","languageName":"Indonesia"},"book":{"id":"PSA","translationId":"ind_web","name":"MAZMUR","commonName":"MAZMUR","title":"Mazmur","order":19,"numberOfChapters":150},"chapter":{"number":24,"content":[{"type":"verse","number":1,"content":["Bumi adalah milik TUHAN dengan segala kepenuhannya;\ndunia, dan orang-orang yang tinggal di dalamnya."]},{"type":"verse","number":2,"content":["Sebab Ia mendirikannya di lautan,\ndan mendirikannya di atas air bah."]},{"type":"verse","number":3,"content":["Siapa yang boleh naik ke bukit TUHAN?\nSiapa yang boleh berdiri di tempat kudusnya?"]},{"type":"verse","number":4,"content":["Orang yang bersih tangannya dan suci hatinya;\nyang tidak meninggikan jiwanya pada kepalsuan,\ndan tidak bersumpah palsu."]},{"type":"verse","number":5,"content":["Dia akan menerima berkat dari Tuhan,\nkebenaran dari Allah yang menyelamatkannya."]},{"type":"verse","number":6,"content":["Inilah angkatan orang-orang yang mencari Dia,\nyang mencari wajahmu—bahkan Yakub.\nSela."]},{"type":"verse","number":7,"content":["Angkat kepalamu, hai gerbang!\nBangkitlah, hai pintu-pintu yang kekal,\ndan Raja Kemuliaan akan datang."]},{"type":"verse","number":8,"content":["Siapakah Raja Kemuliaan?\nTUHAN kuat dan perkasa,\nTuhan perkasa dalam pertempuran."]},{"type":"verse","number":9,"content":["Angkat kepalamu, hai gerbang;\nya, angkatlah, hai pintu-pintu abadi,\ndan Raja Kemuliaan akan datang."]},{"type":"verse","number":10,"content":["Siapakah Raja Kemuliaan ini?\nTUHAN semesta alam adalah Raja Kemuliaan!\nSela."]}]},"numberOfVerses":10}