{"translation":{"id":"zh_web","name":"和合本","shortName":"CUV","englishName":"Chinese Union Version","language":"zho","languageName":"繁體/简体中文"},"book":{"id":"2SA","translationId":"zh_web","name":"撒母耳记下","commonName":"撒母耳记下","title":"撒母耳记下","order":10,"numberOfChapters":24},"chapter":{"number":10,"content":[{"type":"verse","number":1,"content":["这事以后，亚扪人的王死了，他儿子哈嫩接续他作王。"]},{"type":"verse","number":2,"content":["大卫说：“我要以慈爱待拿辖的儿子哈嫩，正如他父亲以慈爱待我一样。”于是大卫差遣臣仆，为他父亲的事去安慰他。大卫的臣仆到了亚扪人的地。"]},{"type":"verse","number":3,"content":["但亚扪人的首领对他们的主哈嫩说：“大卫差人来安慰你，你以为他是在尊敬你的父亲吗？大卫差他的臣仆到你这里来，岂不是为了窥探这城、侦察它，好将它倾覆吗？”"]},{"type":"verse","number":4,"content":["于是哈嫩拿住大卫的臣仆，剃去他们一半的胡须，又从中间割断他们的衣服，直到露出臀部，然后把他们放走。"]},{"type":"verse","number":5,"content":["有人把这事告诉大卫，他就派人去迎接他们，因为这些人非常羞愧。王说：“你们住在耶利哥，等到胡须长起来，然后再回来。”"]},{"type":"verse","number":6,"content":["亚扪人见自己在大卫面前成了可憎的，亚扪人就派人去雇用伯·利合的亚兰人和琐巴的亚兰人，步兵二万人，又雇用玛迦王带一千人，以及陀伯人一万二千人。"]},{"type":"verse","number":7,"content":["大卫听见了，就派约押和勇士的全军出征。"]},{"type":"verse","number":8,"content":["亚扪人出来，在城门口摆阵；琐巴和利合的亚兰人、陀伯人和玛迦人，则另在田野里。"]},{"type":"verse","number":9,"content":["约押看见前后都有战阵对着他，就从以色列所有精兵中挑选人，摆阵迎战亚兰人。"]},{"type":"verse","number":10,"content":["其余的兵交在他兄弟亚比筛手中；亚比筛就摆阵迎战亚扪人。"]},{"type":"verse","number":11,"content":["约押说：“如果亚兰人强过我，你就来帮助我；如果亚扪人强过你，我就来帮助你。"]},{"type":"verse","number":12,"content":["你要刚强！让我们为我们的百姓和我们上帝的城邑刚强；愿耶和华照祂看为好的去行。”"]},{"type":"verse","number":13,"content":["于是约押和跟随他的兵向前进攻亚兰人；亚兰人在他面前逃跑。"]},{"type":"verse","number":14,"content":["亚扪人看见亚兰人逃跑，他们也在亚比筛面前逃跑，进了城。于是约押离开亚扪人，回到耶路撒冷。"]},{"type":"verse","number":15,"content":["亚兰人见自己被以色列击败，就聚集起来。"]},{"type":"verse","number":16,"content":["哈大底谢差人把大河那边的亚兰人调出来；他们来到希兰，有哈大底谢的军长朔巴率领他们。"]},{"type":"verse","number":17,"content":["有人把这事告诉大卫；他就聚集全以色列，过了约旦河，来到希兰。亚兰人摆阵迎战大卫，与他交战。"]},{"type":"verse","number":18,"content":["亚兰人在以色列面前逃跑；大卫杀了亚兰人七百名战车兵和四万名骑兵，又击杀他们的军长朔巴，他就死在那里。"]},{"type":"verse","number":19,"content":["所有臣服于哈大底谢的王看见自己在以色列面前被击败，就与以色列讲和，服侍他们。从此亚兰人不敢再帮助亚扪人了。"]}]},"numberOfVerses":19}