{"translation":{"id":"zh_web","name":"和合本","shortName":"CUV","englishName":"Chinese Union Version","language":"zho","languageName":"繁體/简体中文"},"book":{"id":"PSA","translationId":"zh_web","name":"诗篇","commonName":"诗篇","title":"诗篇","order":19,"numberOfChapters":150},"chapter":{"number":27,"content":[{"type":"verse","number":1,"content":["耶和华是我的亮光，是我的救恩。 我还怕谁呢？ 耶和华是我生命的力量。 我还惧谁呢？"]},{"type":"verse","number":2,"content":["作恶的人临近我，要吞吃我的肉， 就是我的敌人和仇敌，他们却绊跌仆倒。"]},{"type":"verse","number":3,"content":["虽有军队安营攻击我， 我的心也不惧怕。 虽有战争兴起攻击我， 即使如此，我仍要信靠。"]},{"type":"verse","number":4,"content":["有一件事，我曾向耶和华求，这也是我要寻求的： 使我一生一世住在耶和华的殿中， 瞻仰耶和华的荣美， 并在祂的殿里求问。"]},{"type":"verse","number":5,"content":["因为在患难的日子，祂必把我秘密藏在祂的亭中。 在祂帐幕的隐密处，祂必隐藏我。 祂必把我高举在磐石上。"]},{"type":"verse","number":6,"content":["如今我的头必被高举，超过四围的仇敌。 我要在祂的帐棚里献欢喜的祭。 我要歌唱，是的，我要向耶和华歌唱赞美。"]},{"type":"verse","number":7,"content":["耶和华啊，我出声呼求的时候，求你垂听。 也求你怜悯我，应允我。"]},{"type":"verse","number":8,"content":["当你说：“要寻求我的面”时， 我的心对你说：“耶和华啊，我要寻求你的面。”"]},{"type":"verse","number":9,"content":["不要向我隐藏你的面。 不要发怒赶走你的仆人。 你一向是我的帮助。 不要丢弃我， 也不要离弃我，我救恩的上帝啊。"]},{"type":"verse","number":10,"content":["即使我的父母离弃我， 耶和华也必接纳我。"]},{"type":"verse","number":11,"content":["耶和华啊，求你将你的道路指教我。 因我仇敌的缘故，求你引导我走平坦的路。"]},{"type":"verse","number":12,"content":["不要把我交给敌人的愿望， 因为有作假见证的人起来攻击我， 还有吐出残暴之气的人。"]},{"type":"verse","number":13,"content":["我仍然确信这一点： 我必在活人之地看见耶和华的良善。"]},{"type":"verse","number":14,"content":["要等候耶和华。 当刚强，使你的心勇敢。 是的，要等候耶和华。"]}]},"numberOfVerses":14}