{"translation":{"id":"ind_ayt","name":"Alkitab Yang Terbuka","website":"https://ebible.org/Scriptures/details.php?id=indayt","licenseUrl":"https://ebible.org/Scriptures/details.php?id=indayt","licenseNotes":null,"shortName":"AYT","englishName":"Indonesian AYT Bible","language":"ind","textDirection":"ltr","sha256":"4269ef50854c298173e215f3d2d10538056e18bb6fcd32957f34c255d8ecb12f","availableFormats":["json"],"listOfBooksApiLink":"/api/ind_ayt/books.json","numberOfBooks":66,"totalNumberOfChapters":1189,"totalNumberOfVerses":31102,"languageName":"Indonesia","languageEnglishName":"Indonesian"},"book":{"id":"ISA","translationId":"ind_ayt","name":"YESAYA","commonName":"YESAYA","title":"Yesaya","order":23,"numberOfChapters":66,"sha256":"f891415032abc4205058a3f5640978e2960ef78dd8c37c7f0c7c220e7bbb2d1c","firstChapterNumber":1,"firstChapterApiLink":"/api/ind_ayt/ISA/1.json","lastChapterNumber":66,"lastChapterApiLink":"/api/ind_ayt/ISA/66.json","totalNumberOfVerses":1292},"chapter":{"number":17,"content":[{"type":"heading","content":["Nubuat tentang Aram"]},{"type":"verse","number":1,"content":["Inilah pesan ilahi tentang Damsyik:",{"lineBreak":true},{"text":"“Sesungguhnya, Damsyik akan dijatuhkan sehingga tidak lagi menjadi sebuah kota,","poem":1},{"text":"dan akan menjadi timbunan reruntuhan.","poem":2}]},{"type":"verse","number":2,"content":[{"text":"Kota-kota Aroer ditinggalkan,","poem":1},{"text":"mereka akan menjadi tempat kawanan ternak berbaring,","poem":2},{"lineBreak":true},{"text":"dan tidak ada yang menakutkan kawanan ternak.","poem":2}]},{"type":"verse","number":3,"content":[{"text":"Benteng akan dilenyapkan dari Efraim","poem":1},{"text":"dan kerajaan dari Damsyik.","poem":2},{"text":"Sisa-sisa Aram akan menjadi seperti kemuliaan orang Israel,”","poem":1},{"text":"demikianlah firman TUHAN semesta alam.","poem":2}]},{"type":"line_break"},{"type":"verse","number":4,"content":[{"text":"“Pada waktu itu, kemuliaan Yakub akan memudar","poem":1},{"text":"dan tubuh gemuknya akan menjadi kurus.","poem":2}]},{"type":"verse","number":5,"content":[{"text":"Keadaannya bahkan akan seperti penuai yang mengumpulkan gandum yang belum dipotong.","poem":1},{"text":"Lengannya menuai bulir-bulir,","poem":2},{"text":"sama seperti mereka yang memetik bulir-bulir gandum","poem":1},{"text":"di Lembah Refaim.","poem":2}]},{"type":"verse","number":6,"content":[{"text":"Akan tetapi, yang tertinggal akan dibiarkan di dalamnya,","poem":1},{"text":"sama seperti saat menjolok pohon zaitun,","poem":2},{"lineBreak":true},{"text":"dua atau tiga buah zaitun pada dahan yang paling atas,","poem":2},{"text":"empat atau lima buah di dahan-dahan yang penuh buah,”","poem":1},{"text":"firman TUHAN, Allah Israel.","poem":2}]},{"type":"line_break"},{"type":"verse","number":7,"content":["Pada saat itu, manusia akan memandang Penciptanya, dan matanya akan melihat kepada Yang Mahakudus dari Israel."]},{"type":"verse","number":8,"content":["Ia tidak akan memandang mazbah-mazbah buatan tangannya dan tidak akan memperhatikan lagi barang yang dibuat oleh jari-jarinya, ataupun Asyera dan berhala-berhala."]},{"type":"verse","number":9,"content":["Pada waktu itu, kota-kota mereka yang kuat akan ditinggalkan seperti tempat-tempat yang terabaikan di hutan; seperti puncak yang ditinggalkan oleh orang Israel sehingga tanah itu menjadi sunyi sepi."]},{"type":"line_break"},{"type":"verse","number":10,"content":[{"text":"Sebab, kamu telah melupakan Allah keselamatanmu","poem":1},{"text":"dan tidak mengingat Batu Karang perlindunganmu.","poem":2},{"text":"Karena itu, walaupun kamu menanam tanaman-tanaman yang indah","poem":1},{"text":"dan menabur cabang-cabang asing,","poem":2}]},{"type":"verse","number":11,"content":[{"text":"meskipun pada hari kamu menanamnya, kamu memagarinya dengan hati-hati","poem":1},{"text":"dan pada pagi harinya, kamu membuat benihmu bersemi,","poem":2},{"text":"tetapi panenan itu hanya akan menjadi timbunan saja","poem":1},{"text":"pada hari kesakitan","poem":2},{"lineBreak":true},{"text":"dan penderitaan yang tidak tersembuhkan.","poem":2}]},{"type":"line_break"},{"type":"verse","number":12,"content":[{"text":"Wahai!","poem":1},{"text":"Betapa ributnya banyak bangsa, mereka gaduh seperti gemuruh lautan;","poem":2},{"lineBreak":true},{"text":"deru bangsa-bangsa seperti deburan air yang besar.","poem":2}]},{"type":"verse","number":13,"content":[{"text":"Bangsa-bangsa riuh seperti deburan air yang besar,","poem":1},{"text":"tetapi Dia akan menghardik mereka dan mereka akan melarikan diri jauh-jauh,","poem":2},{"text":"diburu seperti sekam di bukit yang tertiup angin,","poem":1},{"text":"seperti debu yang diterbangkan angin puting beliung.","poem":2}]},{"type":"verse","number":14,"content":[{"text":"Pada waktu malam, akan ada kedahsyatan.","poem":1},{"text":"Sebelum pagi tiba, mereka tidak akan ada lagi.","poem":2},{"text":"Itulah bagian orang-orang yang merampok kita;","poem":1},{"text":"undian yang jatuh","poem":2},{"lineBreak":true},{"text":"bagi orang-orang yang menjarah kita.","poem":2}]}],"footnotes":[]},"thisChapterLink":"/api/ind_ayt/ISA/17.json","thisChapterAudioLinks":{},"nextChapterApiLink":"/api/ind_ayt/ISA/18.json","nextChapterAudioLinks":{},"previousChapterApiLink":"/api/ind_ayt/ISA/16.json","previousChapterAudioLinks":{},"numberOfVerses":14}