{"translation":{"id":"zh_web","name":"和合本","shortName":"CUV","englishName":"Chinese Union Version","language":"zho","languageName":"繁體/简体中文"},"book":{"id":"JDG","translationId":"zh_web","name":"士师记","commonName":"士师记","title":"士师记","order":7,"numberOfChapters":21},"chapter":{"number":9,"content":[{"type":"verse","number":1,"content":["耶路巴力的儿子亚比米勒往示剑去，到了他母亲的兄弟那里，对他们和他外祖父全家的人说："]},{"type":"verse","number":2,"content":["“请你们对示剑所有人说：‘是耶路巴力所有的儿子，就是七十个人，都管理你们好呢，还是一个人管理你们好呢？’也请你们记得，我是你们的骨肉。”"]},{"type":"verse","number":3,"content":["他母亲的兄弟就把这一切话替他说给示剑所有人听。他们的心倾向亚比米勒，因为他们说：“他是我们的弟兄。”"]},{"type":"verse","number":4,"content":["他们从巴力·比利土庙里给了他七十块银子；亚比米勒用这些银子雇了一些无用、鲁莽的人，他们就跟随他。"]},{"type":"verse","number":5,"content":["他到俄弗拉他父亲的家，把他的弟兄们，就是耶路巴力的儿子七十个人，杀在一块石头上；但耶路巴力的小儿子约坦还活着，因为他躲藏起来了。"]},{"type":"verse","number":6,"content":["示剑所有人和米罗全家都聚集，去到示剑柱旁的橡树那里，立亚比米勒为王。"]},{"type":"verse","number":7,"content":["有人把这事告诉约坦，他就去，站在基利心山顶上，高声呼喊，对他们说：“示剑人哪，你们要听我，好使上帝也听你们。"]},{"type":"verse","number":8,"content":["众树出去，要膏立一位王来统治它们。它们对橄榄树说：‘请你作我们的王。’"]},{"type":"verse","number":9,"content":["“但橄榄树对它们说：‘我岂可停止出产我的油，就是人藉着我用来尊荣上帝和人的，去在众树之上摇来摇去呢？’"]},{"type":"verse","number":10,"content":["“众树对无花果树说：‘请你来作我们的王。’"]},{"type":"verse","number":11,"content":["“但无花果树对它们说：‘我岂可舍弃我的甘甜和我的美果，去在众树之上摇来摇去呢？’"]},{"type":"verse","number":12,"content":["“众树对葡萄树说：‘请你来作我们的王。’"]},{"type":"verse","number":13,"content":["“葡萄树对它们说：‘我岂可舍弃使上帝和人欢喜的新酒，去在众树之上摇来摇去呢？’"]},{"type":"verse","number":14,"content":["“于是众树都对荆棘说：‘请你来作我们的王。’"]},{"type":"verse","number":15,"content":["“荆棘对众树说：‘如果你们真诚地膏我作你们的王，就来投靠在我的荫下；否则，愿火从荆棘中出来，吞灭黎巴嫩的香柏树。’"]},{"type":"verse","number":16,"content":["“现在，倘若你们立亚比米勒为王，是以诚实和公义行事；倘若你们善待了耶路巴力和他的家，并且照他手所当得的报答了他"]},{"type":"verse","number":17,"content":["（因为我父亲曾为你们争战，冒着性命危险，把你们从米甸人手中救出来；"]},{"type":"verse","number":18,"content":["而你们今日起来攻击我父亲的家，把他的儿子七十个人杀在一块石头上，又立他婢女的儿子亚比米勒作示剑人的王，因为他是你们的弟兄）；"]},{"type":"verse","number":19,"content":["如果你们今日果然以诚实和公义待耶路巴力和他的家，就可以因亚比米勒欢喜，也让他因你们欢喜；"]},{"type":"verse","number":20,"content":["否则，愿火从亚比米勒那里出来，吞灭示剑人和米罗家；又愿火从示剑人和米罗家那里出来，吞灭亚比米勒。”"]},{"type":"verse","number":21,"content":["约坦逃跑，逃到比珥，住在那里，因为惧怕他的弟兄亚比米勒。"]},{"type":"verse","number":22,"content":["亚比米勒作以色列的首领三年。"]},{"type":"verse","number":23,"content":["后来，上帝使一个恶灵在亚比米勒和示剑人之间制造纷争；示剑人就以诡诈待亚比米勒，"]},{"type":"verse","number":24,"content":["为要使耶路巴力七十个儿子所受的强暴归到亚比米勒身上，使他们的血归到杀害他们的弟兄亚比米勒身上，也归到那些支持他杀害自己弟兄的示剑人身上。"]},{"type":"verse","number":25,"content":["示剑人在山顶上设伏兵等候亚比米勒；凡从他们那里经过的人，他们都抢劫。有人把这事告诉了亚比米勒。"]},{"type":"verse","number":26,"content":["以别的儿子迦勒和他的弟兄们来到示剑；示剑人就信靠他。"]},{"type":"verse","number":27,"content":["他们到田间去，收取葡萄园的果子，踹葡萄，举行庆宴，又进他们神的庙中吃喝，咒诅亚比米勒。"]},{"type":"verse","number":28,"content":["以别的儿子迦勒说：“亚比米勒是谁？示剑又是谁，我们竟要服侍他？他不是耶路巴力的儿子吗？西布勒不是他的官员吗？你们去服侍示剑的父亲哈抹的人吧；我们为什么要服侍他呢？"]},{"type":"verse","number":29,"content":["但愿这民归在我手下！那样我就要除掉亚比米勒。”他对亚比米勒说：“增添你的军队，出来吧！”"]},{"type":"verse","number":30,"content":["城的统治者西布勒听见以别的儿子迦勒的话，就怒火中烧。"]},{"type":"verse","number":31,"content":["他暗中派使者到亚比米勒那里，说：“看哪，以别的儿子迦勒和他的弟兄们已经来到示剑；看哪，他们正煽动全城反对你。"]},{"type":"verse","number":32,"content":["现在，你和跟随你的民要夜间上来，在田野埋伏。"]},{"type":"verse","number":33,"content":["到早晨太阳一出来，你就及早起来，冲向这城。看哪，他和跟随他的民出来攻击你的时候，你就照机会所许的对付他们。”"]},{"type":"verse","number":34,"content":["亚比米勒和所有跟随他的民夜间起来，分作四队埋伏，攻击示剑。"]},{"type":"verse","number":35,"content":["以别的儿子迦勒出来，站在城门口。亚比米勒和跟随他的民就从埋伏的地方起来。"]},{"type":"verse","number":36,"content":["迦勒看见那些人，就对西布勒说：“看哪，有人从山顶下来。” 西布勒对他说：“你把山的影子看作人了。”"]},{"type":"verse","number":37,"content":["迦勒又说：“看哪，有人从那地的中央下来，又有一队人从米恶尼尼橡树的路上来。”"]},{"type":"verse","number":38,"content":["西布勒就对他说：“你先前说‘亚比米勒是谁，我们竟要服侍他？’你的口现在在哪里呢？这不是你所轻视的民吗？现在请你出去，与他们交战吧。”"]},{"type":"verse","number":39,"content":["迦勒就率领示剑人出去，与亚比米勒交战。"]},{"type":"verse","number":40,"content":["亚比米勒追赶他，他就在他面前逃跑；许多人受伤倒下，直到城门口。"]},{"type":"verse","number":41,"content":["亚比米勒住在亚鲁玛；西布勒把迦勒和他的弟兄们赶出去，不许他们住在示剑。"]},{"type":"verse","number":42,"content":["次日，民出到田间；有人把这事告诉亚比米勒。"]},{"type":"verse","number":43,"content":["他带着民，把他们分作三队，在田野埋伏；他观看，看哪，民从城里出来。于是他起来攻击他们，击杀他们。"]},{"type":"verse","number":44,"content":["亚比米勒和跟随他的队伍向前冲去，站在城门口；另外两队冲向所有在田野的人，击杀他们。"]},{"type":"verse","number":45,"content":["亚比米勒整天攻打那城；他夺取了那城，杀了城中的人。他拆毁那城，又撒上盐。"]},{"type":"verse","number":46,"content":["示剑楼的所有人听见了，就进了伊勒·比利土殿的堡垒。"]},{"type":"verse","number":47,"content":["有人告诉亚比米勒，示剑楼的所有人都聚集在一起。"]},{"type":"verse","number":48,"content":["亚比米勒和所有跟随他的民上撒们山；亚比米勒手里拿着斧子，砍下树上的一根枝子，拿起来扛在肩上。然后他对跟随他的民说：“你们看见我所做的，就赶快照我所做的去做！”"]},{"type":"verse","number":49,"content":["众人也各自砍下枝子，跟随亚比米勒，把枝子放在堡垒的底部，放火烧堡垒，使火烧在他们身上；这样，示剑楼的所有人也都死了，约有一千男女。"]},{"type":"verse","number":50,"content":["随后亚比米勒往提备斯去，安营攻打提备斯，并夺取了那城。"]},{"type":"verse","number":51,"content":["但城中有一座坚固的楼；城中所有男女都逃到那里，把自己关在里面，又上到楼顶。"]},{"type":"verse","number":52,"content":["亚比米勒来到楼前攻打它，走近楼门，要用火焚烧。"]},{"type":"verse","number":53,"content":["有一个妇人把一块上磨石扔在亚比米勒的头上，打破了他的头骨。"]},{"type":"verse","number":54,"content":["他就急忙叫那给他拿兵器的少年人来，对他说：“拔出你的刀，杀了我，免得人议论我说：‘一个妇人杀了他。’”他的少年人就刺透他，他便死了。"]},{"type":"verse","number":55,"content":["以色列人看见亚比米勒死了，就各自回到自己的地方。"]},{"type":"verse","number":56,"content":["这样，上帝报应了亚比米勒所行的恶，就是他杀害自己七十个弟兄、得罪他父亲的恶；"]},{"type":"verse","number":57,"content":["上帝也把示剑人的一切恶报应在他们头上；耶路巴力的儿子约坦的咒诅就临到他们。"]}]},"numberOfVerses":57}