{"translation":{"id":"zh_web","name":"和合本","shortName":"CUV","englishName":"Chinese Union Version","language":"zho","languageName":"繁體/简体中文"},"book":{"id":"PRO","translationId":"zh_web","name":"箴言","commonName":"箴言","title":"箴言","order":20,"numberOfChapters":31},"chapter":{"number":11,"content":[{"type":"verse","number":1,"content":["虚假的天平是耶和华所憎恶的， 准确的法码却是祂所喜悦的。"]},{"type":"verse","number":2,"content":["骄傲来到，羞辱也随之而来； 谦卑的人却有智慧。"]},{"type":"verse","number":3,"content":["正直人的纯全必引导他们； 奸诈人的乖僻必毁灭他们。"]},{"type":"verse","number":4,"content":["财富在震怒的日子毫无益处， 公义却能救人脱离死亡。"]},{"type":"verse","number":5,"content":["无可指摘之人的义必修直他的道路； 恶人却必因自己的邪恶跌倒。"]},{"type":"verse","number":6,"content":["正直人的义必拯救他们； 不忠信的人却必被恶欲困住。"]},{"type":"verse","number":7,"content":["恶人一死，指望就灭没； 权势的期望也归于无有。"]},{"type":"verse","number":8,"content":["义人蒙拯救脱离患难， 恶人却来代替他的位置。"]},{"type":"verse","number":9,"content":["不敬虔的人用口毁坏邻舍， 义人却借着知识得拯救。"]},{"type":"verse","number":10,"content":["义人亨通，城就欢喜； 恶人灭亡，众人就欢呼。"]},{"type":"verse","number":11,"content":["因正直人的祝福，城得高升； 因恶人的口，城被倾覆。"]},{"type":"verse","number":12,"content":["藐视邻舍的人缺乏智慧； 有聪明的人却静默不言。"]},{"type":"verse","number":13,"content":["搬弄是非的人泄露秘密； 心灵可靠的人却保守隐情。"]},{"type":"verse","number":14,"content":["没有明智的指导，国家就败落； 谋士众多，就有胜利。"]},{"type":"verse","number":15,"content":["为陌生人作保的，必为此受害； 拒绝担保的人却安稳。"]},{"type":"verse","number":16,"content":["有恩德的女子获得尊荣， 强暴的人获得财富。"]},{"type":"verse","number":17,"content":["怜悯人的人善待自己的灵魂； 残忍的人却使自己的肉身受害。"]},{"type":"verse","number":18,"content":["恶人赚得虚假的工价； 撒播公义的人收获可靠的赏赐。"]},{"type":"verse","number":19,"content":["真正行义的人得生命； 追求邪恶的人得死亡。"]},{"type":"verse","number":20,"content":["心中乖僻的人是耶和华所憎恶的； 行事无可指摘的人是祂所喜悦的。"]},{"type":"verse","number":21,"content":["你要确知，恶人必不免受惩罚； 义人的后裔必蒙拯救。"]},{"type":"verse","number":22,"content":["美貌女子缺乏明辨， 如同金环戴在猪鼻上。"]},{"type":"verse","number":23,"content":["义人的愿望只归于善； 恶人的期望却是震怒。"]},{"type":"verse","number":24,"content":["有人施散，反而更加增多； 有人过分吝惜，反致贫穷。"]},{"type":"verse","number":25,"content":["慷慨的人必得丰裕； 滋润人的，自己也必得滋润。"]},{"type":"verse","number":26,"content":["囤积粮食的人，众人咒诅他； 出售粮食的人，福必临到他的头上。"]},{"type":"verse","number":27,"content":["殷勤寻求良善的，是寻求恩惠； 搜寻邪恶的，邪恶必临到他。"]},{"type":"verse","number":28,"content":["倚靠自己财富的人必跌倒； 义人却必如青叶茂盛。"]},{"type":"verse","number":29,"content":["扰害自己家的人必承受风； 愚昧人必作心中有智慧之人的仆人。"]},{"type":"verse","number":30,"content":["义人的果实是生命树； 智慧人赢得灵魂。"]},{"type":"verse","number":31,"content":["看哪，义人在地上尚且受报， 何况恶人和罪人呢！"]}]},"numberOfVerses":31}