{"translation":{"id":"web","name":"World English Bible","shortName":"WEB","englishName":"World English Bible","language":"eng","languageName":"English"},"book":{"id":"JOB","translationId":"web","name":"Job","commonName":"JOB","title":"Job","order":18,"numberOfChapters":42},"chapter":{"number":17,"content":[{"type":"verse","number":1,"content":["“My spirit is consumed.\nMy days are extinct,\nAnd the grave is ready for me."]},{"type":"verse","number":2,"content":["Surely there are mockers with me.\nMy eye dwells on their provocation."]},{"type":"verse","number":3,"content":["“Now give a pledge, be collateral for me with yourself.\nWho is there who will strike hands with me?"]},{"type":"verse","number":4,"content":["For you have hidden their heart from understanding,\nTherefore you shall not exalt them."]},{"type":"verse","number":5,"content":["He who denounces his friends for plunder,\nEven the eyes of his children shall fail."]},{"type":"verse","number":6,"content":["“But he has made me a byword of the people.\nThey spit in my face."]},{"type":"verse","number":7,"content":["My eye also is dim by reason of sorrow.\nAll my members are as a shadow."]},{"type":"verse","number":8,"content":["Upright men shall be astonished at this.\nThe innocent shall stir up himself against the godless."]},{"type":"verse","number":9,"content":["Yet shall the righteous hold on his way.\nHe who has clean hands shall grow stronger and stronger."]},{"type":"verse","number":10,"content":["But as for you all, come on now again;\nI shall not find a wise man among you."]},{"type":"verse","number":11,"content":["My days are past, my plans are broken off,\nas are the thoughts of my heart."]},{"type":"verse","number":12,"content":["They change the night into day,\nsaying ‘The light is near’ in the presence of darkness."]},{"type":"verse","number":13,"content":["If I look for Sheol as my house,\nif I have spread my couch in the darkness,"]},{"type":"verse","number":14,"content":["If I have said to corruption, ‘You are my father;’\nto the worm, ‘My mother,’ and ‘my sister;’"]},{"type":"verse","number":15,"content":["where then is my hope?\nas for my hope, who shall see it?"]},{"type":"verse","number":16,"content":["Shall it go down with me to the gates of Sheol,\nor descend together into the dust?”"]}]},"numberOfVerses":16}