{"translation":{"id":"ind_obo","name":"Alkitab Terjemahan Sederhana Indonesia, Edisi Ketiga","website":"https://ebible.org/Scriptures/details.php?id=ind","licenseUrl":"https://ebible.org/Scriptures/details.php?id=ind","licenseNotes":null,"shortName":"OBO","englishName":"Indonesian Bible (TSI)","language":"ind","textDirection":"ltr","sha256":"01f327eca48c79ec8c0410383f6df1df8f240ba4d772ad1c3a27491176ca3054","availableFormats":["json"],"listOfBooksApiLink":"/api/ind_obo/books.json","numberOfBooks":48,"totalNumberOfChapters":762,"totalNumberOfVerses":20650,"languageName":"Indonesia","languageEnglishName":"Indonesian"},"book":{"id":"ISA","translationId":"ind_obo","name":"Yesaya","commonName":"Yesaya","title":"Yesaya","order":23,"numberOfChapters":66,"sha256":"18925233aaa739e159a813aa3a4bae3ecde6ef1197f2e64ae26711a1a711004f","firstChapterNumber":1,"firstChapterApiLink":"/api/ind_obo/ISA/1.json","lastChapterNumber":66,"lastChapterApiLink":"/api/ind_obo/ISA/66.json","totalNumberOfVerses":1285},"chapter":{"number":19,"content":[{"type":"heading","content":["Nubuat tentang hukuman atas bangsa Mesir"]},{"type":"verse","number":1,"content":["Inilah pesan TUHAN tentang hukuman atas Mesir:",{"text":"Perhatikanlah! TUHAN berkendara di atas awan,","poem":1},{"lineBreak":true},{"text":"melesat cepat menuju Mesir.","poem":1},{"lineBreak":true},{"text":"Dewa-dewa Mesir gemetar melihat kedatangan-Nya","poem":1},{"lineBreak":true},{"text":"dan hati orang-orang Mesir menciut ketakutan.","poem":1}]},{"type":"verse","number":2,"content":["TUHAN berkata:",{"text":"Aku akan membuat orang-orang Mesir memusuhi sesama orang Mesir,","poem":1},{"lineBreak":true},{"text":"sehingga anggota keluarga saling bertengkar,","poem":1},{"lineBreak":true},{"text":"tetangga dengan tetangga saling bertikai,","poem":1},{"lineBreak":true},{"text":"kota dengan kota saling bertempur,","poem":1},{"lineBreak":true},{"text":"dan daerah dengan daerah saling berperang.","poem":1}]},{"type":"verse","number":3,"content":[{"lineBreak":true},{"text":"Maka orang Mesir akan berputus asa.","poem":1},{"text":"Aku akan menggagalkan rencana-rencana mereka","poem":2},{"lineBreak":true},{"text":"sehingga orang Mesir kebingungan.","poem":2},{"lineBreak":true},{"text":"Mereka akan mencari petunjuk dari dewa-dewa, roh-roh orang mati, dan peramal-peramal.","poem":2}]},{"type":"verse","number":4,"content":[{"text":"Aku akan membuat bangsa Mesir ditaklukkan","poem":3},{"lineBreak":true},{"text":"oleh seorang penguasa yang bengis, raja yang kejam.","poem":3},{"lineBreak":true},{"text":"Aku, TUHAN Panglima Semesta, menegaskannya.","poem":3}]},{"type":"line_break"},{"type":"heading","content":["Penglihatan Yesaya tentang bencana kekeringan di Mesir"]},{"type":"verse","number":5,"content":[{"text":"Air sungai Nil akan surut dan habis","poem":1}]},{"type":"verse","number":6,"content":[{"lineBreak":true},{"text":"sehingga anak-anak sungainya pun mengering dan berbau.","poem":1},{"lineBreak":true},{"text":"Maka tumbuhan buluh dan rumput-rumput tinggi di pinggirannya","poem":1},{"lineBreak":true},{"text":"akan mati dan membusuk.","poem":1}]},{"type":"verse","number":7,"content":[{"lineBreak":true},{"text":"Tepian sungai Nil menjadi gersang","poem":1},{"lineBreak":true},{"text":"hingga semua benih yang ditanam di sana mengering,","poem":1},{"lineBreak":true},{"text":"tertiup angin, dan lenyap.","poem":1}]},{"type":"verse","number":8,"content":[{"text":"Para nelayan yang mencari nafkah akan meratap","poem":2},{"lineBreak":true},{"text":"karena kail dan jala mereka tidak berguna lagi.","poem":2}]},{"type":"verse","number":9,"content":[{"text":"Para pembuat kain dan tukang tenun akan berputus asa","poem":3},{"lineBreak":true},{"text":"karena tidak ada lagi bahan baku mereka,","poem":3},{"lineBreak":true},{"text":"yaitu tumbuhan gelagah air dari tepi sungai Nil.","poem":3}]},{"type":"verse","number":10,"content":[{"lineBreak":true},{"text":"Para perajin kain akan bangkrut","poem":3},{"lineBreak":true},{"text":"dan semua buruh bersusah hati.","poem":3}]},{"type":"line_break"},{"type":"heading","content":["Kecaman Yesaya atas Mesir"]},{"type":"verse","number":11,"content":[{"text":"Pejabat-pejabat kota Zoan semuanya bodoh.","poem":1},{"lineBreak":true},{"text":"Para penasihat raja Mesir, bahkan yang paling bijak pun","poem":1},{"lineBreak":true},{"text":"akan memberi petunjuk yang konyol.","poem":1},{"lineBreak":true},{"text":"Berani-beraninya kalian mengaku kepada raja Mesir,","poem":1},{"lineBreak":true},{"text":"“Aku ini murid orang bijak, keturunan raja-raja besar dari zaman kuno.”","poem":1}]},{"type":"verse","number":12,"content":[{"text":"Hai raja Mesir, mana para penasihatmu yang pandai?","poem":2},{"lineBreak":true},{"text":"Kalau mereka benar-benar bijak, biarlah mereka memberitahukan kepadamu","poem":2},{"lineBreak":true},{"text":"tentang apa yang akan dilakukan TUHAN Panglima Semesta terhadap Mesir.","poem":2}]},{"type":"verse","number":13,"content":[{"text":"Para pejabat kota Zoan semuanya bodoh.","poem":3},{"lineBreak":true},{"text":"Para pemuka di kota Memfis meyakini hal-hal yang salah,","poem":3},{"lineBreak":true},{"text":"sehingga pemimpin-pemimpin Mesir menyesatkan rakyat mereka.","poem":3}]},{"type":"verse","number":14,"content":[{"text":"TUHANlah yang telah mengacaukan pikiran mereka.","poem":1},{"lineBreak":true},{"text":"Itu sebabnya mereka mengambil tindakan-tindakan yang salah bagi bangsa Mesir.","poem":1},{"lineBreak":true},{"text":"Mereka linglung, seperti orang mabuk berjalan terhuyung-huyung","poem":1},{"lineBreak":true},{"text":"dan jatuh ke muntahannya sendiri.","poem":1}]},{"type":"verse","number":15,"content":[{"text":"Bangsa Mesir tidak akan mampu berbuat apa-apa.","poem":2},{"lineBreak":true},{"text":"Semuanya tidak berdaya, baik kepala maupun pengikut,","poem":2},{"lineBreak":true},{"text":"baik orang besar maupun rakyat jelata.","poem":2}]},{"type":"verse","number":16,"content":["Pada waktu itu, ketika TUHAN Panglima Semesta menggoncang negeri Mesir, mereka akan gemetar ketakutan seperti perempuan yang lemah."]},{"type":"verse","number":17,"content":["Orang Mesir akan takut kepada orang Yehuda, bahkan mendengar nama Yehuda pun mereka menggigil ketakutan, karena TUHAN Panglima Semesta sudah merencanakan malapetaka atas Mesir."]},{"type":"line_break"},{"type":"heading","content":["Bangsa Mesir kelak akan menyembah TUHAN"]},{"type":"verse","number":18,"content":["Akan tiba saatnya lima kota di Mesir berbicara bahasa Ibrani dan beralih menjadi penyembah TUHAN Panglima Semesta. Salah satu kota itu adalah Heliopolis, Kota Matahari."]},{"type":"verse","number":19,"content":["Pada waktu itu, di pusat negeri Mesir akan dibangun mezbah bagi TUHAN, dan di pinggiran negeri Mesir didirikan tugu untuk menghormati TUHAN."]},{"type":"verse","number":20,"content":["Tugu itu menjadi tanda bahwa bangsa Mesir beribadah kepada TUHAN Panglima Semesta. Maka ketika orang Mesir berseru meminta tolong saat mereka ditindas, TUHAN akan mendatangkan seorang pembela untuk menyelamatkan dan membebaskan mereka."]},{"type":"verse","number":21,"content":["Pada waktu itu, TUHAN akan menyatakan diri-Nya kepada orang Mesir sehingga mereka mengenal dan menyembah Dia. Maka Mesir akan mempersembahkan kurban kepada TUHAN. Mereka akan berjanji untuk beribadah kepada-Nya, lalu menepati janji itu."]},{"type":"verse","number":22,"content":["Memang TUHAN akan menghukum Mesir, tetapi setelah itu Dia akan memulihkan mereka. Orang Mesir akan berbalik kepada TUHAN, maka TUHAN mendengar permohonan mereka dan memulihkan negeri mereka."]},{"type":"verse","number":23,"content":["Pada waktu itu, akan ada jalan besar yang menghubungkan Mesir dengan Asyur, sehingga orang Mesir bebas datang ke Asyur dan orang Asyur bebas datang ke Mesir. Bersama-sama, kedua bangsa itu akan menyembah TUHAN."]},{"type":"verse","number":24,"content":["Pada waktu itu, Israel, bersama dengan Mesir dan Asyur, akan menjadi tiga bangsa terkemuka. Ketiganya menjadi berkat bagi seluruh bumi"]},{"type":"verse","number":25,"content":["karena TUHAN Panglima Semesta memberkati mereka, kata-Nya, “Aku memberkati Mesir, umat-Ku, dan Asyur, ciptaan-Ku, dan Israel, milik-Ku turun temurun.”"]}],"footnotes":[]},"thisChapterLink":"/api/ind_obo/ISA/19.json","thisChapterAudioLinks":{},"nextChapterApiLink":"/api/ind_obo/ISA/20.json","nextChapterAudioLinks":{},"previousChapterApiLink":"/api/ind_obo/ISA/18.json","previousChapterAudioLinks":{},"numberOfVerses":25}