{"translation":{"id":"web","name":"World English Bible","shortName":"WEB","englishName":"World English Bible","language":"eng","languageName":"English"},"book":{"id":"PSA","translationId":"web","name":"Psalms","commonName":"PSALMS","title":"Psalms","order":19,"numberOfChapters":150},"chapter":{"number":122,"content":[{"type":"verse","number":1,"content":["I was glad when they said to me,\n“Let’s go to Yahweh’s house!”"]},{"type":"verse","number":2,"content":["Our feet are standing within your gates, Jerusalem;"]},{"type":"verse","number":3,"content":["Jerusalem, that is built as a city that is compact together;"]},{"type":"verse","number":4,"content":["where the tribes go up, even Yah’s tribes,\naccording to an ordinance for Israel,\nto give thanks to Yahweh’s name."]},{"type":"verse","number":5,"content":["For there are set thrones for judgment,\nthe thrones of David’s house."]},{"type":"verse","number":6,"content":["Pray for the peace of Jerusalem.\nThose who love you will prosper."]},{"type":"verse","number":7,"content":["Peace be within your walls,\nand prosperity within your palaces."]},{"type":"verse","number":8,"content":["For my brothers’ and companions’ sakes,\nI will now say, “Peace be within you.”"]},{"type":"verse","number":9,"content":["For the sake of the house of Yahweh our God,\nI will seek your good."]}]},"numberOfVerses":9}