{"translation":{"id":"zh_web","name":"和合本","shortName":"CUV","englishName":"Chinese Union Version","language":"zho","languageName":"繁體/简体中文"},"book":{"id":"NUM","translationId":"zh_web","name":"民数记","commonName":"民数记","title":"民数记","order":4,"numberOfChapters":36},"chapter":{"number":25,"content":[{"type":"verse","number":1,"content":["以色列人住在什亭；百姓开始与摩押的女子行淫。"]},{"type":"verse","number":2,"content":["这些女子邀请百姓去献祭给她们的神；百姓就吃祭物，并向她们的神下拜。"]},{"type":"verse","number":3,"content":["以色列与巴力·毗珥联合，耶和华的怒气就向以色列发作。"]},{"type":"verse","number":4,"content":["耶和华对摩西说：“把百姓中所有的首领带来，在日头前把他们悬挂在耶和华面前，好使耶和华的烈怒从以色列转消。”"]},{"type":"verse","number":5,"content":["摩西对以色列的审判官说：“你们各人要把属自己的人中与巴力·毗珥联合的都杀了。”"]},{"type":"verse","number":6,"content":["看哪，以色列人中有一个人，当摩西和以色列全会众眼前，在会幕门口哭泣的时候，带着一个米甸女子来到他的弟兄们那里。"]},{"type":"verse","number":7,"content":["祭司亚伦的孙子、以利亚撒的儿子非尼哈看见了，就从会众中起来，手里拿着枪。"]},{"type":"verse","number":8,"content":["他跟随那以色列人进了帐棚，一枪刺穿他们二人，刺穿那以色列男子，也刺穿那女人的身体。这样，瘟疫就在以色列人中止住了。"]},{"type":"verse","number":9,"content":["因瘟疫而死的有二万四千人。"]},{"type":"verse","number":10,"content":["耶和华对摩西说："]},{"type":"verse","number":11,"content":["“祭司亚伦的孙子、以利亚撒的儿子非尼哈，在以色列人中以我的忌邪为忌邪，使我的愤怒从以色列人身上转消，所以我没有在我的忌邪中灭绝以色列人。"]},{"type":"verse","number":12,"content":["因此你要说：‘看哪，我将我的平安之约赐给他。"]},{"type":"verse","number":13,"content":["这约要归给他，也归给他以后的后裔，作为永远祭司职分的约；因为他为他的上帝忌邪，并为以色列人赎罪。’”"]},{"type":"verse","number":14,"content":["那被杀的以色列男子，就是与米甸女子一同被杀的，名叫心利，是撒路的儿子，是西缅人中一个父家的首领。"]},{"type":"verse","number":15,"content":["那被杀的米甸女子名叫哥斯比，是苏珥的女儿；苏珥是米甸一个父家的族长。"]},{"type":"verse","number":16,"content":["耶和华对摩西说："]},{"type":"verse","number":17,"content":["“你要扰害米甸人，击杀他们；"]},{"type":"verse","number":18,"content":["因为他们用诡计扰害你们，在毗珥的事上，并在他们的姊妹、米甸首领的女儿哥斯比的事上欺骗了你们；这哥斯比是在因毗珥的事而发生瘟疫的日子被杀的。”"]}]},"numberOfVerses":18}