{"translation":{"id":"ind_web","name":"World English Bible Terjemahan AI","shortName":"WEB-AI","englishName":"Indonesian AI Translated WEB","language":"ind","languageName":"Indonesia"},"book":{"id":"JOB","translationId":"ind_web","name":"AYUB","commonName":"AYUB","title":"Ayub","order":18,"numberOfChapters":42},"chapter":{"number":9,"content":[{"type":"verse","number":1,"content":["Kemudian Ayub menjawab,"]},{"type":"verse","number":2,"content":["“Sesungguhnya aku tahu, bahwa memang demikian adanya,\ntapi bagaimana manusia bisa adil terhadap Tuhan?"]},{"type":"verse","number":3,"content":["Jika dia senang untuk bersaing dengannya,\ndia tidak bisa menjawabnya satu kali dalam seribu."]},{"type":"verse","number":4,"content":["Tuhan yang bijaksana hatinya, dan perkasa dalam kekuatan:\nsiapakah yang tegar hati terhadapnya dan menjadi makmur?"]},{"type":"verse","number":5,"content":["Dia memindahkan gunung-gunung, padahal mereka tidak mengetahuinya,\nketika dia membalikkan mereka dalam kemarahannya."]},{"type":"verse","number":6,"content":["Dia mengguncangkan bumi dari tempatnya.\nPilar-pilarnya bergetar."]},{"type":"verse","number":7,"content":["Dia memerintahkan matahari, dan matahari tidak terbit,\ndan menyegel bintang-bintang."]},{"type":"verse","number":8,"content":["Dia sendiri yang membentangkan langit,\ndan menginjak ombak laut."]},{"type":"verse","number":9,"content":["Dia membuat Beruang, Orion, dan Pleiades,\ndan kamar di selatan."]},{"type":"verse","number":10,"content":["Dia melakukan hal-hal besar tanpa mencari tahu;\nya, hal-hal menakjubkan yang tak terhitung banyaknya."]},{"type":"verse","number":11,"content":["Lihatlah, dia melewatiku, dan aku tidak melihatnya.\nDia meninggal juga, tapi saya tidak melihatnya."]},{"type":"verse","number":12,"content":["Lihatlah, dia merenggutnya.\nSiapa yang bisa menghalanginya?\nSiapa yang akan bertanya kepadanya, ‘Apa yang sedang kamu lakukan?’"]},{"type":"verse","number":13,"content":["“Tuhan tidak akan menarik amarahnya.\nPara pembantu Rahab membungkuk di bawahnya."]},{"type":"verse","number":14,"content":["Apalagi aku harus menjawabnya,\nDan memilih kata-kataku untuk berdebat dengannya?"]},{"type":"verse","number":15,"content":["Meskipun aku benar, namun aku tidak mau menjawabnya.\nSaya akan mengajukan permohonan kepada hakim saya."]},{"type":"verse","number":16,"content":["Jika aku menelepon, dan dia menjawabku,\nnamun aku tidak percaya dia mendengarkan suaraku."]},{"type":"verse","number":17,"content":["Karena dia menghancurkanku dengan badai,\ndan melipatgandakan lukaku tanpa sebab."]},{"type":"verse","number":18,"content":["Dia tidak akan membiarkanku mengatur napas,\ntapi memenuhiku dengan kepahitan."]},{"type":"verse","number":19,"content":["Kalau soal kekuatan, lihatlah, Dia perkasa!\nJika adil, 'Siapa,' katanya, 'yang akan memanggil saya?'"]},{"type":"verse","number":20,"content":["Sekalipun aku orang benar, mulutku sendirilah yang akan menghukum aku.\nSekalipun aku tidak bersalah, hal itu akan membuktikan bahwa aku jahat."]},{"type":"verse","number":21,"content":["Saya tidak bersalah.\nSaya tidak menghargai diri saya sendiri.\nSaya membenci hidup saya."]},{"type":"verse","number":22,"content":["“Semuanya sama saja.\nOleh karena itu Aku katakan dia membinasakan orang-orang yang tak bercacat dan orang-orang jahat."]},{"type":"verse","number":23,"content":["Jika momok itu membunuh secara tiba-tiba,\ndia akan mengejek persidangan orang yang tidak bersalah."]},{"type":"verse","number":24,"content":["Bumi diserahkan ke tangan orang jahat.\nDia menutupi wajah para hakimnya.\nKalau bukan dia, lalu siapa lagi?"]},{"type":"verse","number":25,"content":["“Sekarang hari-hariku lebih cepat dari seorang pelari.\nMereka melarikan diri, mereka tidak melihat ada gunanya."]},{"type":"verse","number":26,"content":["Mereka telah meninggal dunia bagaikan kapal yang cepat,\nbagaikan elang yang terbang memburu mangsanya."]},{"type":"verse","number":27,"content":["Jika aku berkata, ‘Aku akan melupakan keluhanku,\nAku akan membuang wajah sedihku dan bergembira;’"]},{"type":"verse","number":28,"content":["Aku takut dengan semua kesedihanku,\nSaya tahu bahwa Anda tidak akan menganggap saya tidak bersalah."]},{"type":"verse","number":29,"content":["Saya akan dihukum.\nLalu mengapa usahaku sia-sia?"]},{"type":"verse","number":30,"content":["Jika aku membasuh diriku dengan salju,\ndan bersihkan tanganku dengan alkali,"]},{"type":"verse","number":31,"content":["namun kamu akan menjerumuskanku ke dalam parit.\nPakaianku sendiri akan membuatku muak."]},{"type":"verse","number":32,"content":["Karena dia bukan manusia seperti aku, sehingga aku harus menjawabnya,\nbahwa kita harus bersatu dalam penghakiman."]},{"type":"verse","number":33,"content":["Tidak ada wasit di antara kita,\nitu mungkin akan menimpa kita berdua."]},{"type":"verse","number":34,"content":["Biarkan dia mengambil tongkatnya dariku.\nBiarlah terornya tidak membuatku takut;"]},{"type":"verse","number":35,"content":["maka aku akan berbicara, dan tidak takut padanya,\nkarena aku sendiri tidak begitu."]}]},"numberOfVerses":35}